{"info":{"_postman_id":"ebcb7357-60d8-4923-8cbf-1704bd61ddac","name":"TestBuddy 2022-10-19T21:45:12.883","schema":"https://schema.getpostman.com/json/collection/v2.1.0/collection.json"},"item":[{"name":"Test","description":null,"item":[{"name":"Raw Body","event":null,"request":{"auth":null,"method":"POST","header":[],"body":{"mode":"raw","raw":"username=user@name.com&password=123456&grant_type=password","urlencoded":null,"options":{"raw":{"language":"json"}}},"url":{"raw":"http://localhost:8080/rawBody","protocol":"http","host":["localhost"],"path":["rawBody"]},"headers":{},"data":"username=user@name.com&password=123456&grant_type=password"},"protocolProfileBehavior":null,"response":[{"name":"200 - OK ","originalRequest":{"auth":null,"method":"POST","header":[],"body":{"mode":"raw","raw":"password=123456&grant_type=password&username=user@name.com","urlencoded":null,"options":{"raw":{"language":"json"}}},"url":{"raw":"http://localhost:8080/rawBody","protocol":"http","host":["localhost"],"path":["rawBody"]},"headers":{},"data":"password=123456&grant_type=password&username=user@name.com"},"status":"OK","code":200,"_postman_previewlanguage":"json","header":[],"body":"OK"},{"name":"401 - EMPTY password","originalRequest":{"auth":null,"method":"POST","header":[],"body":{"mode":"raw","raw":"password=&grant_type=password&username=user@name.com","urlencoded":null,"options":{"raw":{"language":"json"}}},"url":{"raw":"http://localhost:8080/rawBody","protocol":"http","host":["localhost"],"path":["rawBody"]},"headers":{},"data":"password=&grant_type=password&username=user@name.com"},"status":"UNAUTHORIZED","code":401,"_postman_previewlanguage":"json","header":[],"body":"Username or password is invalid"},{"name":"400 - EMPTY grant_type","originalRequest":{"auth":null,"method":"POST","header":[],"body":{"mode":"raw","raw":"password=123456&grant_type=&username=user@name.com","urlencoded":null,"options":{"raw":{"language":"json"}}},"url":{"raw":"http://localhost:8080/rawBody","protocol":"http","host":["localhost"],"path":["rawBody"]},"headers":{},"data":"password=123456&grant_type=&username=user@name.com"},"status":"BAD_REQUEST","code":400,"_postman_previewlanguage":"json","header":[],"body":"Invalid grant_type"},{"name":"400 - EMPTY password,grant_type","originalRequest":{"auth":null,"method":"POST","header":[],"body":{"mode":"raw","raw":"password=&grant_type=&username=user@name.com","urlencoded":null,"options":{"raw":{"language":"json"}}},"url":{"raw":"http://localhost:8080/rawBody","protocol":"http","host":["localhost"],"path":["rawBody"]},"headers":{},"data":"password=&grant_type=&username=user@name.com"},"status":"BAD_REQUEST","code":400,"_postman_previewlanguage":"json","header":[],"body":"Invalid grant_type"},{"name":"401 - EMPTY username","originalRequest":{"auth":null,"method":"POST","header":[],"body":{"mode":"raw","raw":"password=123456&grant_type=password&username=","urlencoded":null,"options":{"raw":{"language":"json"}}},"url":{"raw":"http://localhost:8080/rawBody","protocol":"http","host":["localhost"],"path":["rawBody"]},"headers":{},"data":"password=123456&grant_type=password&username="},"status":"UNAUTHORIZED","code":401,"_postman_previewlanguage":"json","header":[],"body":"Username or password is invalid"},{"name":"401 - EMPTY password,username","originalRequest":{"auth":null,"method":"POST","header":[],"body":{"mode":"raw","raw":"password=&grant_type=password&username=","urlencoded":null,"options":{"raw":{"language":"json"}}},"url":{"raw":"http://localhost:8080/rawBody","protocol":"http","host":["localhost"],"path":["rawBody"]},"headers":{},"data":"password=&grant_type=password&username="},"status":"UNAUTHORIZED","code":401,"_postman_previewlanguage":"json","header":[],"body":"Username or password is invalid"},{"name":"400 - EMPTY grant_type,username","originalRequest":{"auth":null,"method":"POST","header":[],"body":{"mode":"raw","raw":"password=123456&grant_type=&username=","urlencoded":null,"options":{"raw":{"language":"json"}}},"url":{"raw":"http://localhost:8080/rawBody","protocol":"http","host":["localhost"],"path":["rawBody"]},"headers":{},"data":"password=123456&grant_type=&username="},"status":"BAD_REQUEST","code":400,"_postman_previewlanguage":"json","header":[],"body":"Invalid grant_type"},{"name":"400 - EMPTY password,grant_type,username","originalRequest":{"auth":null,"method":"POST","header":[],"body":{"mode":"raw","raw":"password=&grant_type=&username=","urlencoded":null,"options":{"raw":{"language":"json"}}},"url":{"raw":"http://localhost:8080/rawBody","protocol":"http","host":["localhost"],"path":["rawBody"]},"headers":{},"data":"password=&grant_type=&username="},"status":"BAD_REQUEST","code":400,"_postman_previewlanguage":"json","header":[],"body":"Invalid grant_type"},{"name":"401 - INVALID password","originalRequest":{"auth":null,"method":"POST","header":[],"body":{"mode":"raw","raw":"password=123456_INVALID&grant_type=password&username=user@name.com","urlencoded":null,"options":{"raw":{"language":"json"}}},"url":{"raw":"http://localhost:8080/rawBody","protocol":"http","host":["localhost"],"path":["rawBody"]},"headers":{},"data":"password=123456_INVALID&grant_type=password&username=user@name.com"},"status":"UNAUTHORIZED","code":401,"_postman_previewlanguage":"json","header":[],"body":"Username or password is invalid"},{"name":"400 - INVALID grant_type","originalRequest":{"auth":null,"method":"POST","header":[],"body":{"mode":"raw","raw":"password=123456&grant_type=password_INVALID&username=user@name.com","urlencoded":null,"options":{"raw":{"language":"json"}}},"url":{"raw":"http://localhost:8080/rawBody","protocol":"http","host":["localhost"],"path":["rawBody"]},"headers":{},"data":"password=123456&grant_type=password_INVALID&username=user@name.com"},"status":"BAD_REQUEST","code":400,"_postman_previewlanguage":"json","header":[],"body":"Invalid grant_type"},{"name":"400 - INVALID password,grant_type","originalRequest":{"auth":null,"method":"POST","header":[],"body":{"mode":"raw","raw":"password=123456_INVALID&grant_type=password_INVALID&username=user@name.com","urlencoded":null,"options":{"raw":{"language":"json"}}},"url":{"raw":"http://localhost:8080/rawBody","protocol":"http","host":["localhost"],"path":["rawBody"]},"headers":{},"data":"password=123456_INVALID&grant_type=password_INVALID&username=user@name.com"},"status":"BAD_REQUEST","code":400,"_postman_previewlanguage":"json","header":[],"body":"Invalid grant_type"},{"name":"401 - INVALID username","originalRequest":{"auth":null,"method":"POST","header":[],"body":{"mode":"raw","raw":"password=123456&grant_type=password&username=user@name.com_INVALID","urlencoded":null,"options":{"raw":{"language":"json"}}},"url":{"raw":"http://localhost:8080/rawBody","protocol":"http","host":["localhost"],"path":["rawBody"]},"headers":{},"data":"password=123456&grant_type=password&username=user@name.com_INVALID"},"status":"UNAUTHORIZED","code":401,"_postman_previewlanguage":"json","header":[],"body":"Username or password is invalid"},{"name":"401 - INVALID password,username","originalRequest":{"auth":null,"method":"POST","header":[],"body":{"mode":"raw","raw":"password=123456_INVALID&grant_type=password&username=user@name.com_INVALID","urlencoded":null,"options":{"raw":{"language":"json"}}},"url":{"raw":"http://localhost:8080/rawBody","protocol":"http","host":["localhost"],"path":["rawBody"]},"headers":{},"data":"password=123456_INVALID&grant_type=password&username=user@name.com_INVALID"},"status":"UNAUTHORIZED","code":401,"_postman_previewlanguage":"json","header":[],"body":"Username or password is invalid"},{"name":"400 - INVALID grant_type,username","originalRequest":{"auth":null,"method":"POST","header":[],"body":{"mode":"raw","raw":"password=123456&grant_type=password_INVALID&username=user@name.com_INVALID","urlencoded":null,"options":{"raw":{"language":"json"}}},"url":{"raw":"http://localhost:8080/rawBody","protocol":"http","host":["localhost"],"path":["rawBody"]},"headers":{},"data":"password=123456&grant_type=password_INVALID&username=user@name.com_INVALID"},"status":"BAD_REQUEST","code":400,"_postman_previewlanguage":"json","header":[],"body":"Invalid grant_type"},{"name":"400 - INVALID password,grant_type,username","originalRequest":{"auth":null,"method":"POST","header":[],"body":{"mode":"raw","raw":"password=123456_INVALID&grant_type=password_INVALID&username=user@name.com_INVALID","urlencoded":null,"options":{"raw":{"language":"json"}}},"url":{"raw":"http://localhost:8080/rawBody","protocol":"http","host":["localhost"],"path":["rawBody"]},"headers":{},"data":"password=123456_INVALID&grant_type=password_INVALID&username=user@name.com_INVALID"},"status":"BAD_REQUEST","code":400,"_postman_previewlanguage":"json","header":[],"body":"Invalid grant_type"},{"name":"400 - MISSING password","originalRequest":{"auth":null,"method":"POST","header":[],"body":{"mode":"raw","raw":"grant_type=password&username=user@name.com","urlencoded":null,"options":{"raw":{"language":"json"}}},"url":{"raw":"http://localhost:8080/rawBody","protocol":"http","host":["localhost"],"path":["rawBody"]},"headers":{},"data":"grant_type=password&username=user@name.com"},"status":"BAD_REQUEST","code":400,"_postman_previewlanguage":"json","header":[],"body":"Missing parameter"},{"name":"400 - MISSING grant_type","originalRequest":{"auth":null,"method":"POST","header":[],"body":{"mode":"raw","raw":"password=123456&username=user@name.com","urlencoded":null,"options":{"raw":{"language":"json"}}},"url":{"raw":"http://localhost:8080/rawBody","protocol":"http","host":["localhost"],"path":["rawBody"]},"headers":{},"data":"password=123456&username=user@name.com"},"status":"BAD_REQUEST","code":400,"_postman_previewlanguage":"json","header":[],"body":"Missing parameter"},{"name":"400 - MISSING password,grant_type","originalRequest":{"auth":null,"method":"POST","header":[],"body":{"mode":"raw","raw":"username=user@name.com","urlencoded":null,"options":{"raw":{"language":"json"}}},"url":{"raw":"http://localhost:8080/rawBody","protocol":"http","host":["localhost"],"path":["rawBody"]},"headers":{},"data":"username=user@name.com"},"status":"BAD_REQUEST","code":400,"_postman_previewlanguage":"json","header":[],"body":"Invalid body"},{"name":"400 - MISSING username","originalRequest":{"auth":null,"method":"POST","header":[],"body":{"mode":"raw","raw":"password=123456&grant_type=password","urlencoded":null,"options":{"raw":{"language":"json"}}},"url":{"raw":"http://localhost:8080/rawBody","protocol":"http","host":["localhost"],"path":["rawBody"]},"headers":{},"data":"password=123456&grant_type=password"},"status":"BAD_REQUEST","code":400,"_postman_previewlanguage":"json","header":[],"body":"Missing parameter"},{"name":"400 - MISSING password,username","originalRequest":{"auth":null,"method":"POST","header":[],"body":{"mode":"raw","raw":"grant_type=password","urlencoded":null,"options":{"raw":{"language":"json"}}},"url":{"raw":"http://localhost:8080/rawBody","protocol":"http","host":["localhost"],"path":["rawBody"]},"headers":{},"data":"grant_type=password"},"status":"BAD_REQUEST","code":400,"_postman_previewlanguage":"json","header":[],"body":"Invalid body"},{"name":"400 - MISSING grant_type,username","originalRequest":{"auth":null,"method":"POST","header":[],"body":{"mode":"raw","raw":"password=123456","urlencoded":null,"options":{"raw":{"language":"json"}}},"url":{"raw":"http://localhost:8080/rawBody","protocol":"http","host":["localhost"],"path":["rawBody"]},"headers":{},"data":"password=123456"},"status":"BAD_REQUEST","code":400,"_postman_previewlanguage":"json","header":[],"body":"Invalid body"},{"name":"400 - MISSING password,grant_type,username","originalRequest":{"auth":null,"method":"POST","header":[],"body":{"mode":"raw","raw":"","urlencoded":null,"options":{"raw":{"language":"json"}}},"url":{"raw":"http://localhost:8080/rawBody","protocol":"http","host":["localhost"],"path":["rawBody"]},"headers":{},"data":""},"status":"BAD_REQUEST","code":400,"_postman_previewlanguage":"json","header":[],"body":"Invalid body"}]}]},{"name":"Second","description":null,"item":[{"name":"Custom Header","event":null,"request":{"auth":null,"method":"GET","header":[],"body":null,"url":{"raw":"localhost:8080/customHeader","protocol":null,"host":["localhost"],"path":["customHeader"]},"headers":{},"data":""},"protocolProfileBehavior":null,"response":[]},{"name":"Age","event":null,"request":{"auth":null,"method":"POST","header":[],"body":null,"url":{"raw":"http://localhost:8080/age?age=40","protocol":"http","host":["localhost"],"path":["age"]},"headers":{},"data":""},"protocolProfileBehavior":null,"response":[]},{"name":"Simple","event":null,"request":{"auth":null,"method":"GET","header":[],"body":null,"url":{"raw":"http://localhost:8080/simple","protocol":"http","host":["localhost"],"path":["simple"]},"headers":{},"data":""},"protocolProfileBehavior":null,"response":[]}]}],"folderLookup":{"Second":{"name":"Second","description":null,"item":[{"name":"Custom Header","event":null,"request":{"auth":null,"method":"GET","header":[],"body":null,"url":{"raw":"localhost:8080/customHeader","protocol":null,"host":["localhost"],"path":["customHeader"]},"headers":{},"data":""},"protocolProfileBehavior":null,"response":[]},{"name":"Age","event":null,"request":{"auth":null,"method":"POST","header":[],"body":null,"url":{"raw":"http://localhost:8080/age?age=40","protocol":"http","host":["localhost"],"path":["age"]},"headers":{},"data":""},"protocolProfileBehavior":null,"response":[]},{"name":"Simple","event":null,"request":{"auth":null,"method":"GET","header":[],"body":null,"url":{"raw":"http://localhost:8080/simple","protocol":"http","host":["localhost"],"path":["simple"]},"headers":{},"data":""},"protocolProfileBehavior":null,"response":[]}]},"Test":{"name":"Test","description":null,"item":[{"name":"Raw Body","event":null,"request":{"auth":null,"method":"POST","header":[],"body":{"mode":"raw","raw":"username=user@name.com&password=123456&grant_type=password","urlencoded":null,"options":{"raw":{"language":"json"}}},"url":{"raw":"http://localhost:8080/rawBody","protocol":"http","host":["localhost"],"path":["rawBody"]},"headers":{},"data":"username=user@name.com&password=123456&grant_type=password"},"protocolProfileBehavior":null,"response":[{"name":"200 - OK ","originalRequest":{"auth":null,"method":"POST","header":[],"body":{"mode":"raw","raw":"password=123456&grant_type=password&username=user@name.com","urlencoded":null,"options":{"raw":{"language":"json"}}},"url":{"raw":"http://localhost:8080/rawBody","protocol":"http","host":["localhost"],"path":["rawBody"]},"headers":{},"data":"password=123456&grant_type=password&username=user@name.com"},"status":"OK","code":200,"_postman_previewlanguage":"json","header":[],"body":"OK"},{"name":"401 - EMPTY password","originalRequest":{"auth":null,"method":"POST","header":[],"body":{"mode":"raw","raw":"password=&grant_type=password&username=user@name.com","urlencoded":null,"options":{"raw":{"language":"json"}}},"url":{"raw":"http://localhost:8080/rawBody","protocol":"http","host":["localhost"],"path":["rawBody"]},"headers":{},"data":"password=&grant_type=password&username=user@name.com"},"status":"UNAUTHORIZED","code":401,"_postman_previewlanguage":"json","header":[],"body":"Username or password is invalid"},{"name":"400 - EMPTY grant_type","originalRequest":{"auth":null,"method":"POST","header":[],"body":{"mode":"raw","raw":"password=123456&grant_type=&username=user@name.com","urlencoded":null,"options":{"raw":{"language":"json"}}},"url":{"raw":"http://localhost:8080/rawBody","protocol":"http","host":["localhost"],"path":["rawBody"]},"headers":{},"data":"password=123456&grant_type=&username=user@name.com"},"status":"BAD_REQUEST","code":400,"_postman_previewlanguage":"json","header":[],"body":"Invalid grant_type"},{"name":"400 - EMPTY password,grant_type","originalRequest":{"auth":null,"method":"POST","header":[],"body":{"mode":"raw","raw":"password=&grant_type=&username=user@name.com","urlencoded":null,"options":{"raw":{"language":"json"}}},"url":{"raw":"http://localhost:8080/rawBody","protocol":"http","host":["localhost"],"path":["rawBody"]},"headers":{},"data":"password=&grant_type=&username=user@name.com"},"status":"BAD_REQUEST","code":400,"_postman_previewlanguage":"json","header":[],"body":"Invalid grant_type"},{"name":"401 - EMPTY username","originalRequest":{"auth":null,"method":"POST","header":[],"body":{"mode":"raw","raw":"password=123456&grant_type=password&username=","urlencoded":null,"options":{"raw":{"language":"json"}}},"url":{"raw":"http://localhost:8080/rawBody","protocol":"http","host":["localhost"],"path":["rawBody"]},"headers":{},"data":"password=123456&grant_type=password&username="},"status":"UNAUTHORIZED","code":401,"_postman_previewlanguage":"json","header":[],"body":"Username or password is invalid"},{"name":"401 - EMPTY password,username","originalRequest":{"auth":null,"method":"POST","header":[],"body":{"mode":"raw","raw":"password=&grant_type=password&username=","urlencoded":null,"options":{"raw":{"language":"json"}}},"url":{"raw":"http://localhost:8080/rawBody","protocol":"http","host":["localhost"],"path":["rawBody"]},"headers":{},"data":"password=&grant_type=password&username="},"status":"UNAUTHORIZED","code":401,"_postman_previewlanguage":"json","header":[],"body":"Username or password is invalid"},{"name":"400 - EMPTY grant_type,username","originalRequest":{"auth":null,"method":"POST","header":[],"body":{"mode":"raw","raw":"password=123456&grant_type=&username=","urlencoded":null,"options":{"raw":{"language":"json"}}},"url":{"raw":"http://localhost:8080/rawBody","protocol":"http","host":["localhost"],"path":["rawBody"]},"headers":{},"data":"password=123456&grant_type=&username="},"status":"BAD_REQUEST","code":400,"_postman_previewlanguage":"json","header":[],"body":"Invalid grant_type"},{"name":"400 - EMPTY password,grant_type,username","originalRequest":{"auth":null,"method":"POST","header":[],"body":{"mode":"raw","raw":"password=&grant_type=&username=","urlencoded":null,"options":{"raw":{"language":"json"}}},"url":{"raw":"http://localhost:8080/rawBody","protocol":"http","host":["localhost"],"path":["rawBody"]},"headers":{},"data":"password=&grant_type=&username="},"status":"BAD_REQUEST","code":400,"_postman_previewlanguage":"json","header":[],"body":"Invalid grant_type"},{"name":"401 - INVALID password","originalRequest":{"auth":null,"method":"POST","header":[],"body":{"mode":"raw","raw":"password=123456_INVALID&grant_type=password&username=user@name.com","urlencoded":null,"options":{"raw":{"language":"json"}}},"url":{"raw":"http://localhost:8080/rawBody","protocol":"http","host":["localhost"],"path":["rawBody"]},"headers":{},"data":"password=123456_INVALID&grant_type=password&username=user@name.com"},"status":"UNAUTHORIZED","code":401,"_postman_previewlanguage":"json","header":[],"body":"Username or password is invalid"},{"name":"400 - INVALID grant_type","originalRequest":{"auth":null,"method":"POST","header":[],"body":{"mode":"raw","raw":"password=123456&grant_type=password_INVALID&username=user@name.com","urlencoded":null,"options":{"raw":{"language":"json"}}},"url":{"raw":"http://localhost:8080/rawBody","protocol":"http","host":["localhost"],"path":["rawBody"]},"headers":{},"data":"password=123456&grant_type=password_INVALID&username=user@name.com"},"status":"BAD_REQUEST","code":400,"_postman_previewlanguage":"json","header":[],"body":"Invalid grant_type"},{"name":"400 - INVALID password,grant_type","originalRequest":{"auth":null,"method":"POST","header":[],"body":{"mode":"raw","raw":"password=123456_INVALID&grant_type=password_INVALID&username=user@name.com","urlencoded":null,"options":{"raw":{"language":"json"}}},"url":{"raw":"http://localhost:8080/rawBody","protocol":"http","host":["localhost"],"path":["rawBody"]},"headers":{},"data":"password=123456_INVALID&grant_type=password_INVALID&username=user@name.com"},"status":"BAD_REQUEST","code":400,"_postman_previewlanguage":"json","header":[],"body":"Invalid grant_type"},{"name":"401 - INVALID username","originalRequest":{"auth":null,"method":"POST","header":[],"body":{"mode":"raw","raw":"password=123456&grant_type=password&username=user@name.com_INVALID","urlencoded":null,"options":{"raw":{"language":"json"}}},"url":{"raw":"http://localhost:8080/rawBody","protocol":"http","host":["localhost"],"path":["rawBody"]},"headers":{},"data":"password=123456&grant_type=password&username=user@name.com_INVALID"},"status":"UNAUTHORIZED","code":401,"_postman_previewlanguage":"json","header":[],"body":"Username or password is invalid"},{"name":"401 - INVALID password,username","originalRequest":{"auth":null,"method":"POST","header":[],"body":{"mode":"raw","raw":"password=123456_INVALID&grant_type=password&username=user@name.com_INVALID","urlencoded":null,"options":{"raw":{"language":"json"}}},"url":{"raw":"http://localhost:8080/rawBody","protocol":"http","host":["localhost"],"path":["rawBody"]},"headers":{},"data":"password=123456_INVALID&grant_type=password&username=user@name.com_INVALID"},"status":"UNAUTHORIZED","code":401,"_postman_previewlanguage":"json","header":[],"body":"Username or password is invalid"},{"name":"400 - INVALID grant_type,username","originalRequest":{"auth":null,"method":"POST","header":[],"body":{"mode":"raw","raw":"password=123456&grant_type=password_INVALID&username=user@name.com_INVALID","urlencoded":null,"options":{"raw":{"language":"json"}}},"url":{"raw":"http://localhost:8080/rawBody","protocol":"http","host":["localhost"],"path":["rawBody"]},"headers":{},"data":"password=123456&grant_type=password_INVALID&username=user@name.com_INVALID"},"status":"BAD_REQUEST","code":400,"_postman_previewlanguage":"json","header":[],"body":"Invalid grant_type"},{"name":"400 - INVALID password,grant_type,username","originalRequest":{"auth":null,"method":"POST","header":[],"body":{"mode":"raw","raw":"password=123456_INVALID&grant_type=password_INVALID&username=user@name.com_INVALID","urlencoded":null,"options":{"raw":{"language":"json"}}},"url":{"raw":"http://localhost:8080/rawBody","protocol":"http","host":["localhost"],"path":["rawBody"]},"headers":{},"data":"password=123456_INVALID&grant_type=password_INVALID&username=user@name.com_INVALID"},"status":"BAD_REQUEST","code":400,"_postman_previewlanguage":"json","header":[],"body":"Invalid grant_type"},{"name":"400 - MISSING password","originalRequest":{"auth":null,"method":"POST","header":[],"body":{"mode":"raw","raw":"grant_type=password&username=user@name.com","urlencoded":null,"options":{"raw":{"language":"json"}}},"url":{"raw":"http://localhost:8080/rawBody","protocol":"http","host":["localhost"],"path":["rawBody"]},"headers":{},"data":"grant_type=password&username=user@name.com"},"status":"BAD_REQUEST","code":400,"_postman_previewlanguage":"json","header":[],"body":"Missing parameter"},{"name":"400 - MISSING grant_type","originalRequest":{"auth":null,"method":"POST","header":[],"body":{"mode":"raw","raw":"password=123456&username=user@name.com","urlencoded":null,"options":{"raw":{"language":"json"}}},"url":{"raw":"http://localhost:8080/rawBody","protocol":"http","host":["localhost"],"path":["rawBody"]},"headers":{},"data":"password=123456&username=user@name.com"},"status":"BAD_REQUEST","code":400,"_postman_previewlanguage":"json","header":[],"body":"Missing parameter"},{"name":"400 - MISSING password,grant_type","originalRequest":{"auth":null,"method":"POST","header":[],"body":{"mode":"raw","raw":"username=user@name.com","urlencoded":null,"options":{"raw":{"language":"json"}}},"url":{"raw":"http://localhost:8080/rawBody","protocol":"http","host":["localhost"],"path":["rawBody"]},"headers":{},"data":"username=user@name.com"},"status":"BAD_REQUEST","code":400,"_postman_previewlanguage":"json","header":[],"body":"Invalid body"},{"name":"400 - MISSING username","originalRequest":{"auth":null,"method":"POST","header":[],"body":{"mode":"raw","raw":"password=123456&grant_type=password","urlencoded":null,"options":{"raw":{"language":"json"}}},"url":{"raw":"http://localhost:8080/rawBody","protocol":"http","host":["localhost"],"path":["rawBody"]},"headers":{},"data":"password=123456&grant_type=password"},"status":"BAD_REQUEST","code":400,"_postman_previewlanguage":"json","header":[],"body":"Missing parameter"},{"name":"400 - MISSING password,username","originalRequest":{"auth":null,"method":"POST","header":[],"body":{"mode":"raw","raw":"grant_type=password","urlencoded":null,"options":{"raw":{"language":"json"}}},"url":{"raw":"http://localhost:8080/rawBody","protocol":"http","host":["localhost"],"path":["rawBody"]},"headers":{},"data":"grant_type=password"},"status":"BAD_REQUEST","code":400,"_postman_previewlanguage":"json","header":[],"body":"Invalid body"},{"name":"400 - MISSING grant_type,username","originalRequest":{"auth":null,"method":"POST","header":[],"body":{"mode":"raw","raw":"password=123456","urlencoded":null,"options":{"raw":{"language":"json"}}},"url":{"raw":"http://localhost:8080/rawBody","protocol":"http","host":["localhost"],"path":["rawBody"]},"headers":{},"data":"password=123456"},"status":"BAD_REQUEST","code":400,"_postman_previewlanguage":"json","header":[],"body":"Invalid body"},{"name":"400 - MISSING password,grant_type,username","originalRequest":{"auth":null,"method":"POST","header":[],"body":{"mode":"raw","raw":"","urlencoded":null,"options":{"raw":{"language":"json"}}},"url":{"raw":"http://localhost:8080/rawBody","protocol":"http","host":["localhost"],"path":["rawBody"]},"headers":{},"data":""},"status":"BAD_REQUEST","code":400,"_postman_previewlanguage":"json","header":[],"body":"Invalid body"}]}]}}}